aliyunsdkschedulerx3/__init__.py
aliyunsdkschedulerx3/request/__init__.py
aliyunsdkschedulerx3/request/v20240624/CreateAppRequest.py
aliyunsdkschedulerx3/request/v20240624/CreateClusterRequest.py
aliyunsdkschedulerx3/request/v20240624/CreateJobRequest.py
aliyunsdkschedulerx3/request/v20240624/DeleteAppRequest.py
aliyunsdkschedulerx3/request/v20240624/DeleteClusterRequest.py
aliyunsdkschedulerx3/request/v20240624/DeleteJobsRequest.py
aliyunsdkschedulerx3/request/v20240624/ExportJobsRequest.py
aliyunsdkschedulerx3/request/v20240624/GetClusterRequest.py
aliyunsdkschedulerx3/request/v20240624/GetDesigateInfoRequest.py
aliyunsdkschedulerx3/request/v20240624/GetJobExecutionProgressRequest.py
aliyunsdkschedulerx3/request/v20240624/GetLogRequest.py
aliyunsdkschedulerx3/request/v20240624/ImportCalendarRequest.py
aliyunsdkschedulerx3/request/v20240624/ImportJobsRequest.py
aliyunsdkschedulerx3/request/v20240624/ListAlarmEventRequest.py
aliyunsdkschedulerx3/request/v20240624/ListAppNamesRequest.py
aliyunsdkschedulerx3/request/v20240624/ListAppsRequest.py
aliyunsdkschedulerx3/request/v20240624/ListCalendarNamesRequest.py
aliyunsdkschedulerx3/request/v20240624/ListClustersRequest.py
aliyunsdkschedulerx3/request/v20240624/ListExecutorsRequest.py
aliyunsdkschedulerx3/request/v20240624/ListJobExecutionsRequest.py
aliyunsdkschedulerx3/request/v20240624/ListJobsRequest.py
aliyunsdkschedulerx3/request/v20240624/ListLablesRequest.py
aliyunsdkschedulerx3/request/v20240624/ListRegionZoneRequest.py
aliyunsdkschedulerx3/request/v20240624/ListRegionsRequest.py
aliyunsdkschedulerx3/request/v20240624/ListScheduleEventRequest.py
aliyunsdkschedulerx3/request/v20240624/ListScheduleTimesRequest.py
aliyunsdkschedulerx3/request/v20240624/OperateDesignateExecutorsRequest.py
aliyunsdkschedulerx3/request/v20240624/OperateDisableJobsRequest.py
aliyunsdkschedulerx3/request/v20240624/OperateEnableJobsRequest.py
aliyunsdkschedulerx3/request/v20240624/OperateExecuteJobRequest.py
aliyun_python_sdk_schedulerx3-1.0.0.dist-info/LICENSE
aliyun_python_sdk_schedulerx3-1.0.0.dist-info/METADATA
aliyun_python_sdk_schedulerx3-1.0.0.dist-info/WHEEL
aliyun_python_sdk_schedulerx3-1.0.0.dist-info/top_level.txt
aliyun_python_sdk_schedulerx3-1.0.0.dist-info/RECORD
